{
    "en": {
        "DISAF01": "Malaria-Affected People No ",
        "DISAF02": "Diarrhea-Affected People No ",
        "DISAF03": "TB-Affected People No ",
        "DISAF04": "Dysentery-Affected People No ",
        "DISAF05": "Hepatitis-Affected People No ",
        "DISAF06": "Pneumonia-Affected People No ",
        "DISAF07": "Typhoid-Affected People No ",
        "DISAF08": "ARI-Affected People No ",
        "DISAF09": "Poison-Affected People No ",
        "DISAF10": "Flu-Affected People No ",
        "DISAF11": "Flu-Affected People No ",
        "DISAF12": "High Blood Pressure-Affected People No ",
        "DISAF13": "Stomahache-Affected People No ",
        "DISAF14": "Respiratory Disease-Affected People No ",
        "DISAF15": "Injured-Affected People No ",
        "DISAF16": "Snake Bite-Affected People No ",
        "DISAF17": "H1N1-Affected People No "
    },
    "mm": {
        "DISAF01": "ငှက်ဖျား-ဖြစ်ပွားဦးရေ",
        "DISAF02": "ဝမ်းလျှော-ဖြစ်ပွားဦးရေ",
        "DISAF03": "တီဘီ-ဖြစ်ပွားဦးရေ",
        "DISAF04": "ဝမ်းကိုက်-ဖြစ်ပွားဦးရေ",
        "DISAF05": "အသဲရောင်-ဖြစ်ပွားဦးရေ",
        "DISAF06": "အဆုတ်ရောင်-ဖြစ်ပွားဦးရေ",
        "DISAF07": "အူရောင်ငန်းဖျား-ဖြစ်ပွားဦးရေ",
        "DISAF08": "အေအာအိုင်-ဖြစ်ပွားဦးရေ",
        "DISAF09": "အဆိပ်သင့်-ဖြစ်ပွားဦးရေ",
        "DISAF10": "တုပ်ကွေး-ဖြစ်ပွားဦးရေ",
        "DISAF11": "သွေးလွန်တုပ် ကွေး-ဖြစ်ပွားဦးရေ",
        "DISAF12": "သွေးတိုး-ဖြစ်ပွားဦးရေ",
        "DISAF13": "အစာအိမ်-ဖြစ်ပွားဦးရေ",
        "DISAF14": "အသက်ရှူလမ်းကြောင်းပိုးဝင်-ဖြစ်ပွားဦးရေ",
        "DISAF15": "ထိခိုက်ရှနာ-ဖြစ်ပွားဦးရေ",
        "DISAF16": "မြွေကိုက်-ဖြစ်ပွားဦးရေ",
        "DISAF17": "H1N1-ဖြစ်ပွားဦးရေ"
    }
}